LICENSE.md
MANIFEST.in
README.md
setup.py
admin_gradient/__init__.py
admin_gradient/admin.py
admin_gradient/apps.py
admin_gradient/forms.py
admin_gradient/urls.py
admin_gradient/utils.py
admin_gradient/views.py
admin_gradient/migrations/__init__.py
admin_gradient/static/.gitkeep
admin_gradient/static/assets/css/forms.css
admin_gradient/static/assets/css/style.css
admin_gradient/static/assets/css/widgets.css
admin_gradient/static/assets/css/plugins/animate.min.css
admin_gradient/static/assets/css/plugins/bootstrap.min.css
admin_gradient/static/assets/css/plugins/perfect-scrollbar.css
admin_gradient/static/assets/fonts/fa-brands-400.eot
admin_gradient/static/assets/fonts/fa-brands-400.svg
admin_gradient/static/assets/fonts/fa-brands-400.ttf
admin_gradient/static/assets/fonts/fa-brands-400.woff
admin_gradient/static/assets/fonts/fa-brands-400.woff2
admin_gradient/static/assets/fonts/fa-regular-400.eot
admin_gradient/static/assets/fonts/fa-regular-400.svg
admin_gradient/static/assets/fonts/fa-regular-400.ttf
admin_gradient/static/assets/fonts/fa-regular-400.woff
admin_gradient/static/assets/fonts/fa-regular-400.woff2
admin_gradient/static/assets/fonts/fa-solid-900.eot
admin_gradient/static/assets/fonts/fa-solid-900.svg
admin_gradient/static/assets/fonts/fa-solid-900.ttf
admin_gradient/static/assets/fonts/fa-solid-900.woff
admin_gradient/static/assets/fonts/fa-solid-900.woff2
admin_gradient/static/assets/fonts/feather.eot
admin_gradient/static/assets/fonts/feather.svg
admin_gradient/static/assets/fonts/feather.ttf
admin_gradient/static/assets/fonts/feather.woff
admin_gradient/static/assets/fonts/pct.eot
admin_gradient/static/assets/fonts/pct.svg
admin_gradient/static/assets/fonts/pct.ttf
admin_gradient/static/assets/fonts/pct.woff
admin_gradient/static/assets/fonts/poppins/pxiByp8kv8JHgFVrLEj6Z11lFc-K.woff2
admin_gradient/static/assets/fonts/poppins/pxiByp8kv8JHgFVrLEj6Z1JlFc-K.woff2
admin_gradient/static/assets/fonts/poppins/pxiByp8kv8JHgFVrLEj6Z1xlFQ.woff2
django_admin_gradient.egg-info/PKG-INFO
django_admin_gradient.egg-info/SOURCES.txt
django_admin_gradient.egg-info/dependency_links.txt
django_admin_gradient.egg-info/not-zip-safe
django_admin_gradient.egg-info/top_level.txt
